htmst/__init__.py
htmst/parser.py
htmst/py.typed
htmst/structures.py
htmst-1.0a9.dist-info/LICENCE
htmst-1.0a9.dist-info/METADATA
htmst-1.0a9.dist-info/WHEEL
htmst-1.0a9.dist-info/top_level.txt
htmst-1.0a9.dist-info/RECORD
