Metadata-Version: 2.1
Name: htmst
Version: 1.0a9
Summary: HTML to AST with positions
Author-email: Al Mahdi <picometproject@gmail.com>
License: MIT
Project-URL: Funding, https://buymeacoffee.com/almahdi404
Project-URL: Repository, https://github.com/picomet/htmst
Keywords: html,parser,ast,position
Classifier: Intended Audience :: Developers
Classifier: License :: OSI Approved :: MIT License
Classifier: Programming Language :: Python :: 3
Classifier: Programming Language :: Python :: 3.12
Classifier: Programming Language :: Python :: 3.13
Classifier: Typing :: Typed
Requires-Python: >=3.12
License-File: LICENCE
